[
  {
    "name": "Austria",
    "code": "AT",
    "market": 8999,
    "default_language": "en"
  },
  {
    "name": "Australia",
    "code": "AU",
    "market": 8999,
    "default_language": "en"
  },
  {
    "name": "Belgium",
    "code": "BE",
    "market": 8999,
    "default_language": "en"
  },
  {
    "name": "Bolivia",
    "code": "BO",
    "market": 8999,
    "default_language": "en"
  },
  {
    "name": "Brazil",
    "code": "BR",
    "market": 8999,
    "default_language": "en"
  },
  {
    "name": "Canada",
    "code": "CA",
    "market": 8999,
    "default_language": "en"
  },
  {
    "name": "Chile",
    "code": "CH",
    "market": 8999,
    "default_language": "en"
  },
  {
    "name": "China",
    "code": "CN",
    "market": 8999,
    "default_language": "en"
  },
  {
    "name": "Denmark",
    "code": "DK",
    "market": 8999,
    "default_language": "en"
  },
  {
    "name": "Finland",
    "code": "FI",
    "market": 8999,
    "default_language": "en"
  },
  {
    "name": "France",
    "code": "FR",
    "market": 8999,
    "default_language": "en"
  },
  {
    "name": "Germany",
    "code": "DE",
    "market": 8999,
    "default_language": "en"
  },
  {
    "name": "Hong Kong",
    "code": "HK",
    "market": 8999,
    "default_language": "en"
  },
  {
    "name": "India",
    "code": "IN",
    "market": 8999,
    "default_language": "en"
  },  
  {
    "name": "Indonesia",
    "code": "ID",
    "market": 8999,
    "default_language": "en"
  },
  {
    "name": "Ireland",
    "code": "IE",
    "market": 8999,
    "default_language": "en"
  },
  {
    "name": "Iceland",
    "code": "IS",
    "market": 8999,
    "default_language": "en"
  },
  {
    "name": "Italy",
    "code": "IT",
    "market": 8999,
    "default_language": "en"
  },
  {
    "name": "Japan",
    "code": "JP",
    "market": 8999,
    "default_language": "en"
  },
  {
    "name": "Korea",
    "code": "KR",
    "market": 8999,
    "default_language": "en"
  },
  {
    "name": "Mexico",
    "code": "MX",
    "market": 8999,
    "default_language": "en"
  },
  {
    "name": "Netherlands",
    "code": "NL",
    "market": 8999,
    "default_language": "en"
  },
  {
    "name": "Nigeria",
    "code": "NG",
    "market": 8999,
    "default_language": "en"
  },
  {
    "name": "Norway",
    "code": "NO",
    "market": 8999,
    "default_language": "en"
  },
  {
    "name": "Poland",
    "code": "PL",
    "market": 8999,
    "default_language": "en"
  },
  {
    "name": "Portugal",
    "code": "PT",
    "market": 8999,
    "default_language": "en"
  },
  {
    "name": "Russia",
    "code": "RU",
    "market": 8999,
    "default_language": "en"
  },
  {
    "name": "Saudi Arabia",
    "code": "SA",
    "market": 8999,
    "default_language": "en"
  },
  {
    "name": "Singapore",
    "code": "SG",
    "market": 8999,
    "default_language": "en"
  },
  {
    "name": "South Africa",
    "code": "ZA",
    "market": 8999,
    "default_language": "en"
  },
  {
    "name": "Spain",
    "code": "ES",
    "market": 1234,
    "default_language": "it"
  },
  {
    "name": "Sweden",
    "code": "SE",
    "market": 8999,
    "default_language": "en"
  },
  {
    "name": "Switzerland",
    "code": "CH",
    "market": 8999,
    "default_language": "en"
  },
  {
    "name": "Turkey",
    "code": "TR",
    "market": 8999,
    "default_language": "en"
  },
  {
    "name": "United Kingdom",
    "code": "GB",
    "market": 8999,
    "default_language": "en"
  },
  {
    "name": "United States",
    "code": "US",
    "market": 8999,
    "default_language": "en"
  }
]